{"chunk_definitions":[{"row":33,"row_count":1,"visible":true,"expansion_state":0,"options":{"include":false,"engine":"r","label":"setup"},"document_id":"EEDE851F","chunk_id":"csetup_chunk","chunk_label":"setup"},{"row":46,"row_count":1,"visible":true,"expansion_state":0,"options":{"engine":"r","label":"unnamed-chunk-5"},"document_id":"EEDE851F","chunk_id":"c6d79jjj54n8b","chunk_label":"unnamed-chunk-2"},{"row":63,"row_count":1,"visible":true,"expansion_state":0,"options":{"engine":"r","message":false,"label":"unnamed-chunk-13"},"document_id":"EEDE851F","chunk_id":"crxaanu4x5dgc","chunk_label":"unnamed-chunk-3"}],"doc_write_time":1639490753,"working_dir":null,"default_chunk_options":{},"chunk_rendered_width":700}